loudify/__init__.py
loudify/broker.py
loudify/broker_api.py
loudify/broker_service_api.py
loudify/broker_worker_api.py
loudify/cli.py
loudify/client.py
loudify/client_async_api.py
loudify/client_sync_api.py
loudify/definitions.py
loudify/parser.py
loudify/worker.py
loudify/worker_api.py
loudify/zhelpers.py
loudify-0.0.post40.dist-info/entry_points.txt
loudify-0.0.post40.dist-info/LICENSE
loudify-0.0.post40.dist-info/WHEEL
loudify-0.0.post40.dist-info/METADATA
loudify-0.0.post40.dist-info/RECORD
