Metadata-Version: 2.1
Name: loudify
Version: 0.0.post40
Summary: Initialisation module for loudify broker.
Home-page: https://github.com/martynvdijke/loudify
Author: Martyn van Dijke
Author-email: martijnvdijke600@gmail.com
Classifier: License :: OSI Approved :: MIT License
Requires-Dist: flit_core>=2.2.0
Requires-Dist: coloredlogs
Requires-Dist: setuptools_scm
Requires-Dist: pyzmq
